{
  "db_name": "PostgreSQL",
  "query": "SELECT\n    id,\n    command_type AS \"command_type: InternalCommandType\",\n    receiver_id,\n    fee,\n    hash\nFROM internal_commands;\n",
  "describe": {
    "columns": [
      {
        "ordinal": 0,
        "name": "id",
        "type_info": "Int4"
      },
      {
        "ordinal": 1,
        "name": "command_type: InternalCommandType",
        "type_info": {
          "Custom": {
            "name": "internal_command_type",
            "kind": {
              "Enum": [
                "fee_transfer_via_coinbase",
                "fee_transfer",
                "coinbase"
              ]
            }
          }
        }
      },
      {
        "ordinal": 2,
        "name": "receiver_id",
        "type_info": "Int4"
      },
      {
        "ordinal": 3,
        "name": "fee",
        "type_info": "Text"
      },
      {
        "ordinal": 4,
        "name": "hash",
        "type_info": "Text"
      }
    ],
    "parameters": {
      "Left": []
    },
    "nullable": [
      false,
      false,
      false,
      false,
      false
    ]
  },
  "hash": "524fbf9f4e4c3b56dc6e0e196d8b65aa1b9b50941ecfe22e2f69c1076a598fac"
}
